stepai/__info__.py
stepai/__init__.py
stepai-0.0.1.dist-info/METADATA
stepai-0.0.1.dist-info/WHEEL
stepai-0.0.1.dist-info/top_level.txt
stepai-0.0.1.dist-info/RECORD
