Metadata-Version: 2.1
Name: stepai
Version: 0.0.1
Summary: stepai
Home-page: https://github.com/DIYer22/stepai
Author: DIYer22
Author-email: ylxx@live.com
Classifier: Topic :: Software Development :: Libraries :: Python Modules
Classifier: Programming Language :: Python :: 3
Classifier: License :: OSI Approved :: MIT License
Classifier: Operating System :: OS Independent
Requires-Dist: boxx
